aboba/__init__.py
aboba/base/__init__.py
aboba/base/base_aboba.py
aboba/base/base_data_sampler.py
aboba/base/base_data_source.py
aboba/base/base_effect_modifier.py
aboba/base/base_processors.py
aboba/base/base_test.py
aboba/design/__init__.py
aboba/design/base_designer.py
aboba/design/basic_designer.py
aboba/design/time_based_designer.py
aboba/effect_modifiers/__init__.py
aboba/effect_modifiers/group_modifier.py
aboba/effect_modifiers/time_based_modifier.py
aboba/experiment/__init__.py
aboba/experiment/aboba_experiment.py
aboba/experiment/experiment_data.py
aboba/experiment/experiment_group.py
aboba/experiment/visualization.py
aboba/pipeline/__init__.py
aboba/pipeline/pipeline.py
aboba/processing/__init__.py
aboba/processing/bucket_processor.py
aboba/processing/cuped_processor.py
aboba/processing/ensure_cols_processor.py
aboba/processing/preprocessor_pipeline.py
aboba/processing/regression_processor.py
aboba/processing/rename_cols_processor.py
aboba/samplers/__init__.py
aboba/samplers/group_sampler.py
aboba/samplers/random_sampler.py
aboba/samplers/stratified_sampler.py
aboba/samplers/user_sampler.py
aboba/tests/__init__.py
aboba/tests/absolute_ttest.py
aboba/tests/cuped_lreg.py
aboba/tests/relative_ttest.py
aboba/tests/stratified_ttest.py
aboba/tests/multiple/__init__.py
aboba/tests/multiple/bartlet.py
aboba/tests/multiple/dunn.py
aboba/tests/multiple/f_test.py
aboba/tests/multiple/hsd.py
aboba/tests/multiple/kruskal.py
aboba/tests/ratio/__init__.py
aboba/tests/ratio/delta_ratio.py
aboba/tests/ratio/linearization_ratio.py
aboba/utils/__init__.py
aboba/utils/alpha_interval.py
aboba/utils/draw.py
aboba/utils/logging.py
aboba/utils/p_value.py
aboba/utils/ratio_metric.py
aboba/utils/time_based_data_generator.py
aboba-1.0.2.dist-info/METADATA
aboba-1.0.2.dist-info/WHEEL
aboba-1.0.2.dist-info/top_level.txt
aboba-1.0.2.dist-info/RECORD
