Metadata-Version: 2.4
Name: aboba
Version: 1.0.2
Summary: AB tests library with simplicity in mind
Author-email: Max Gorishniy <gorishniy@alexdremov.me>, Alex Dremov <alex@alexdremov.me>
Classifier: Programming Language :: Python :: 3
Classifier: License :: OSI Approved :: MIT License
Classifier: Operating System :: OS Independent
Requires-Python: >=3.9
Requires-Dist: pandas>=1.5.0
Requires-Dist: joblib>=1.0.0
Requires-Dist: tqdm>=4.60.0
Requires-Dist: numpy>=1.23.0
Requires-Dist: scipy>=1.10.0
Requires-Dist: matplotlib>=3.7.0
Requires-Dist: statsmodels>=0.13.0
Requires-Dist: seaborn>=0.12.0
Requires-Dist: scikit-posthocs>=0.9.0
Requires-Dist: pydantic
Provides-Extra: testing
Requires-Dist: pytest>=7.4.0; extra == "testing"
Requires-Dist: pytest-cov>=4.1.0; extra == "testing"
Requires-Dist: pytest-xdist>=3.3.0; extra == "testing"
Provides-Extra: docs
Requires-Dist: sphinx; extra == "docs"
Requires-Dist: myst-parser; extra == "docs"
Requires-Dist: furo; extra == "docs"
Requires-Dist: sphinx-autodoc-typehints; extra == "docs"
Requires-Dist: linkify-it-py; extra == "docs"
